Workbook

Sheet Expenditures
A1: Expenditure Tracker
A2: Grant for Congress (MO-02) — log every disbursement. Itemize payees over $200.
A4: Date | B4: Payee | C4: Address | D4: Purpose | E4: Category | F4: Amount | G4: Method | H4: Itemize? (>$200) | I4: Invoice # | J4: Notes
H5: =IF(F5="","",IF(F5>200,"YES",""))
H6: =IF(F6="","",IF(F6>200,"YES",""))
H7: =IF(F7="","",IF(F7>200,"YES",""))
H8: =IF(F8="","",IF(F8>200,"YES",""))
H9: =IF(F9="","",IF(F9>200,"YES",""))
H10: =IF(F10="","",IF(F10>200,"YES",""))
H11: =IF(F11="","",IF(F11>200,"YES",""))
H12: =IF(F12="","",IF(F12>200,"YES",""))
H13: =IF(F13="","",IF(F13>200,"YES",""))
H14: =IF(F14="","",IF(F14>200,"YES",""))
H15: =IF(F15="","",IF(F15>200,"YES",""))
H16: =IF(F16="","",IF(F16>200,"YES",""))
... H204: =IF(F204="","",IF(F204>200,"YES",""))
E205: TOTAL SPENT: | F205: =SUM(F5:F204)

Sheet By Category
A1: Spending by Category
A3: Category | B3: Total
A4: Voter Contact | B4: =SUMIF(Expenditures!$E:$E,A4,Expenditures!$F:$F)
A5: Mail | B5: =SUMIF(Expenditures!$E:$E,A5,Expenditures!$F:$F)
A6: Digital Ads | B6: =SUMIF(Expenditures!$E:$E,A6,Expenditures!$F:$F)
A7: Printing | B7: =SUMIF(Expenditures!$E:$E,A7,Expenditures!$F:$F)
A8: Staff/Payroll | B8: =SUMIF(Expenditures!$E:$E,A8,Expenditures!$F:$F)
A9: Consulting | B9: =SUMIF(Expenditures!$E:$E,A9,Expenditures!$F:$F)
A10: Events | B10: =SUMIF(Expenditures!$E:$E,A10,Expenditures!$F:$F)
A11: Office/Admin | B11: =SUMIF(Expenditures!$E:$E,A11,Expenditures!$F:$F)
A12: Travel | B12: =SUMIF(Expenditures!$E:$E,A12,Expenditures!$F:$F)
A13: Fundraising | B13: =SUMIF(Expenditures!$E:$E,A13,Expenditures!$F:$F)
A14: Compliance | B14: =SUMIF(Expenditures!$E:$E,A14,Expenditures!$F:$F)
A15: Other | B15: =SUMIF(Expenditures!$E:$E,A15,Expenditures!$F:$F)

Sheet Instructions
A1: EXPENDITURE TRACKER — how to use
A3: 1. Log every disbursement with payee, purpose, and category.
A4: 2. Payments over $200 to a payee must be itemized in FEC reports ('Itemize?' = YES).
A5: 3. The 'By Category' tab auto-totals spending so you can watch your budget mix.
A6: 4. Reconcile this tracker to your bank statement before every reporting deadline.
A8: Educational template, not legal/financial advice. Verify itemization rules at fec.gov.
